scrapy_zenrows/__init__.py
scrapy_zenrows/__version__.py
scrapy_zenrows/api_key_handler.py
scrapy_zenrows/middleware.py
scrapy_zenrows/zenrows_request.py
scrapy_zenrows-1.0.0.dist-info/LICENSE
scrapy_zenrows-1.0.0.dist-info/METADATA
scrapy_zenrows-1.0.0.dist-info/WHEEL
scrapy_zenrows-1.0.0.dist-info/top_level.txt
scrapy_zenrows-1.0.0.dist-info/RECORD
