Metadata-Version: 2.1
Name: scrapy-zenrows
Version: 1.0.0
Summary: A Scrapy middleware for accessing ZenRows Scraper API with minimal setup.
Home-page: https://github.com/ZenRows/scrapy-zenrows-middleware
Author: Idowu Omisola and Yuvraj Chandra
Author-email: support@zenrows.com
License: MIT
Classifier: Programming Language :: Python :: 3
Classifier: License :: OSI Approved :: MIT License
Classifier: Operating System :: OS Independent
License-File: LICENSE
Requires-Dist: scrapy
